pike/__init__.py
pike/__main__.py
pike/py.typed
pike/task.py
pike/utils.py
pike/cli/__init__.py
pike/cli/config.py
pike/cli/validate.py
pike_tasks-0.0.1.dist-info/LICENSE
pike_tasks-0.0.1.dist-info/METADATA
pike_tasks-0.0.1.dist-info/WHEEL
pike_tasks-0.0.1.dist-info/entry_points.txt
pike_tasks-0.0.1.dist-info/top_level.txt
pike_tasks-0.0.1.dist-info/RECORD
