Metadata-Version: 2.1
Name: pike-tasks
Version: 0.0.1
Summary: Like make, but Python
Home-page: https://github.com/RealOrangeOne/pike
Author: Jake Howard
License: BSD
Project-URL: Changelog, https://github.com/RealOrangeOne/pike/releases
Project-URL: Issues, https://github.com/RealOrangeOne/pike/issues
Platform: UNKNOWN
Classifier: Development Status :: 4 - Beta
Classifier: Intended Audience :: Developers
Classifier: Intended Audience :: Education
Classifier: Intended Audience :: Information Technology
Classifier: Programming Language :: Python
Classifier: Programming Language :: Python :: 3
Classifier: Programming Language :: Python :: 3.7
Classifier: Programming Language :: Python :: 3.8
Classifier: Programming Language :: Python :: 3.9
Classifier: Programming Language :: Python :: Implementation :: CPython
Classifier: Topic :: Software Development
Classifier: Typing :: Typed
Requires-Python: >=3.7
Requires-Dist: docstring-parser
